lel_lang-0.0.6.dist-info/DESCRIPTION.rst
lel_lang-0.0.6.dist-info/METADATA
lel_lang-0.0.6.dist-info/RECORD
lel_lang-0.0.6.dist-info/WHEEL
lel_lang-0.0.6.dist-info/entry_points.txt
lel_lang-0.0.6.dist-info/metadata.json
lel_lang-0.0.6.dist-info/top_level.txt
pylel/__init__.py
pylel/interpreter.py
pylel/parse.py
pylel/repl.py
pylel/token.py
pylel/tools.py
pylel/evaluate/__init__.py
pylel/evaluate/scope.py
pylel/evaluate/evaluate_expr/__init__.py
pylel/evaluate/evaluate_expr/find_base_path.py
pylel/evaluate/evaluate_expr/language_core/__init__.py
pylel/evaluate/evaluate_expr/language_core/lel_apply.py
pylel/evaluate/evaluate_expr/language_core/lel_call.py
pylel/evaluate/evaluate_expr/language_core/lel_call_function.py
pylel/evaluate/evaluate_expr/language_core/lel_filter.py
pylel/evaluate/evaluate_expr/language_core/lel_function.py
pylel/evaluate/evaluate_expr/language_core/lel_if.py
pylel/evaluate/evaluate_expr/language_core/lel_import.py
pylel/evaluate/evaluate_expr/language_core/lel_lambda.py
pylel/evaluate/evaluate_expr/language_core/lel_let.py
pylel/evaluate/evaluate_expr/language_core/lel_list.py
pylel/evaluate/evaluate_expr/language_core/lel_map.py
pylel/evaluate/evaluate_expr/language_core/lel_mutate.py
pylel/evaluate/evaluate_expr/language_core/lel_use.py
pylel/evaluate/evaluate_expr/language_core/standard_language_functions/__init__.py
pylel/evaluate/evaluate_expr/language_core/standard_language_functions/lel_bit.py
pylel/evaluate/evaluate_expr/language_core/standard_language_functions/lel_boolean.py
pylel/evaluate/evaluate_expr/language_core/standard_language_functions/lel_general.py
pylel/evaluate/evaluate_expr/language_core/standard_language_functions/lel_list.py
pylel/evaluate/evaluate_expr/language_core/standard_language_functions/lel_math.py
pylel/evaluate/evaluate_expr/language_core/standard_language_functions/lel_string.py
pylel/extensions/__init__.py
pylel/extensions/read_file_sync.py
pylel/libraries/__init__.py
pylel/libraries/math.py
