Metadata-Version: 2.0
Name: lel-lang
Version: 0.0.6
Summary: Lel programming language(Lisp-esque language)
Home-page: https://github.com/osaatcioglu/Lisp-esque-language
Author: Ömer Saatcioglu
Author-email: osaatcioglu@gmail.com
License: MIT
Keywords: compiler lisp lel parser ast tokenize
Platform: UNKNOWN
Classifier: Development Status :: 3 - Alpha
Classifier: Intended Audience :: Developers
Classifier: Intended Audience :: Education
Classifier: Topic :: Software Development :: Compilers
Classifier: License :: OSI Approved :: MIT License
Classifier: Programming Language :: Python :: 3
Requires-Dist: py-require
Requires-Dist: six
Provides-Extra: dev
Provides-Extra: test
